core/__init__.py
core/utils.py
neurokime-0.0.0.dist-info/LICENSE
neurokime-0.0.0.dist-info/METADATA
neurokime-0.0.0.dist-info/WHEEL
neurokime-0.0.0.dist-info/top_level.txt
neurokime-0.0.0.dist-info/RECORD
